CMSC 132/exercise2.vhdl
-- Jan Coleen S. Estilo
-- CMSC 132 - ST7L

entity exercise2 is
    port (temp, co, moisture, gl : in bit; fix, evac : out bit);
end exercise2;

architecture rtl of exercise2 is
    begin
        fix <= (temp and moisture);
        evac <= ((co or gl) or (gl and temp));
end rtl;

CMSC 132/exercise2_tb.vhdl
-- Jan Coleen S. Estilo
-- CMSC 132 - ST7L

entity exercise2_tb is
end exercise2_tb;

architecture behav of exercise2_tb is
    component exercise2
        port (temp, co, moisture, gl : in bit; fix, evac : out bit);
    end component;
    for exercise2_0: exercise2 use entity work.exercise2;
    signal inputtemp, inputco, inputmoisture, inputgl, outputfix, outputevac : bit;
begin
    exercise2_0: exercise2 port map (temp => inputtemp, co => inputco, moisture => inputmoisture, gl => inputgl, fix => outputfix, evac => outputevac);


    process
        type pattern_type is record
            inputtemp, inputco, inputmoisture, inputgl : bit;

            outputfix, outputevac : bit;
        end record;

        type pattern_array is array (natural range <>) of pattern_type;
        constant patterns : pattern_array :=
           (('0', '0', '0', '0', '0', '0'),
            ('0', '0', '0', '1', '0', '1'),
            ('0', '0', '1', '0', '0', '0'),
            ('0', '0', '1', '1', '0', '1'),
            ('0', '1', '0', '0', '0', '1'),
            ('0', '1', '0', '1', '0', '1'),
            ('0', '1', '1', '0', '0', '1'),
            ('0', '1', '1', '1', '0', '1'),
            ('1', '0', '0', '0', '0', '0'),
            ('1', '0', '0', '1', '0', '1'),
            ('1', '0', '1', '0', '1', '0'),
            ('1', '0', '1', '1', '1', '1'),
            ('1', '1', '0', '0', '0', '1'),
            ('1', '1', '0', '1', '0', '1'),
            ('1', '1', '1', '0', '1', '1'),
            ('1', '1', '1', '1', '1', '1'));

    begin
        for i in patterns'range loop
            inputtemp <= patterns(i).inputtemp;
            inputco <= patterns(i).inputco;
            inputmoisture <= patterns(i).inputmoisture;
            inputgl <= patterns(i).inputgl;

            wait for 1 ns;

            assert outputfix = patterns(i).outputfix
                report "bad and value" severity error;
            
            assert outputevac = patterns(i).outputevac
                report "bad and or value" severity error;
        end loop;

        assert false report "end of test" severity note;

        wait;
    end process;
end behav;

CMSC 132/exercise2/exercise2.vcd
$date
  Thu Sep 15 22:27:38 2022
$end
$version
  GHDL v0
$end
$timescale
  1 fs
$end
$scope module standard $end
$upscope $end
$scope module exercise2_tb $end
$var reg 1 ! inputtemp $end
$var reg 1 " inputco $end
$var reg 1 # inputmoisture $end
$var reg 1 $ inputgl $end
$var reg 1 % outputfix $end
$var reg 1 & outputevac $end
$scope module exercise2_0 $end
$var reg 1 ' temp $end
$var reg 1 ( co $end
$var reg 1 ) moisture $end
$var reg 1 * gl $end
$var reg 1 + fix $end
$var reg 1 , evac $end
$upscope $end
$upscope $end
$enddefinitions $end
#0
0!
0"
0#
0$
0%
0&
0'
0(
0)
0*
0+
0,
#1000000
1$
1&
1*
1,
#2000000
1#
0$
0&
1)
0*
0,
#3000000
1$
1&
1*
1,
#4000000
1"
0#
0$
1(
0)
0*
#5000000
1$
1*
#6000000
1#
0$
1)
0*
#7000000
1$
1*
#8000000
1!
0"
0#
0$
0&
1'
0(
0)
0*
0,
#9000000
1$
1&
1*
1,
#10000000
1#
0$
1%
0&
1)
0*
1+
0,
#11000000
1$
1&
1*
1,
#12000000
1"
0#
0$
0%
1(
0)
0*
0+
#13000000
1$
1*
#14000000
1#
0$
1%
1)
0*
1+
#15000000
1$
1*
