CMSC 132/week4/exercise4_estilo/mplus.vhdl
-- Jan Coleen S. Estilo
-- CMSC 132 - ST7L

library ieee;
use ieee.std_logic_1164.all;

entity mplus is
    port(clk, Min, Pin : in std_logic;
            Gout: out std_logic;
            Sout: out std_logic);
end mplus;

architecture behav of mplus is
    begin
        process(clk, Min, Pin)
            begin
            if(falling_edge(clk) and Pin = 'X') then
                if(Min = '0') then
                    Gout <= '0';
                    Sout <= '0';
                elsif(Min = '1') then
                    Gout <= '1';
                    Sout <= '1';
                end if;
            end if;
        end process;
end behav;

CMSC 132/week4/exercise4_estilo/mplus_tb.vhdl
-- Jan Coleen S. Estilo
-- CMSC 132 ST7L

library ieee;
use ieee.std_logic_1164.all;

entity mplus_tb is
end entity;

architecture rtl of mplus_tb is
    signal Min : std_logic:='0';
    signal Pin : std_logic:='X';
    signal Gout : std_logic;
    signal Sout : std_logic;
    signal clk : std_logic := '0';
    component mplus is
        port(clk, Min, Pin : in std_logic; Gout: out std_logic; Sout: out std_logic);
    end component;

begin
    mp: mplus port map(clk=>clk, Min=>Min, Pin=>Pin, Gout=>Gout, Sout=>Sout);
    process
    begin
        for i in 1 to 10 loop
            clk <= not clk;
            wait for 3 ns;
            if(i mod 3 = 0) then
                if(i>5) then
                    Min <= '0';
                    Pin <= 'X';
                elsif(i<=5) then
                    Min <= '1';
                    Pin <= 'X';
                end if;
            end if;
            wait for 1.65 ns;
            if(i mod 2 = 0) then
                if(i>5) then
                    Pin <= '1';
                    Min <= 'X';
                elsif(i<=5) then
                    Pin <= '0';
                    Min <= 'X';
                end if;
                wait for 2.88 ns;
            end if;
        end loop;
        wait;
    end process;
end architecture;

CMSC 132/week4/exercise4_estilo/mplus_tb.vcd
$date
  Fri Sep 30 17:58:04 2022
$end
$version
  GHDL v0
$end
$timescale
  1 fs
$end
$scope module standard $end
$upscope $end
$scope module std_logic_1164 $end
$upscope $end
$scope module mplus_tb $end
$var reg 1 ! min $end
$var reg 1 " pin $end
$var reg 1 # gout $end
$var reg 1 $ sout $end
$var reg 1 % clk $end
$scope module mp $end
$var reg 1 & clk $end
$var reg 1 ' min $end
$var reg 1 ( pin $end
$var reg 1 ) gout $end
$var reg 1 * sout $end
$upscope $end
$upscope $end
$enddefinitions $end
#0
0!
X"
U#
U$
1%
1&
0'
X(
U)
U*
#3000000
#4650000
0#
0$
0%
0&
0)
0*
#7650000
#9300000
X!
0"
X'
0(
#12180000
1%
1&
#15180000
1!
X"
1'
X(
#16830000
1#
1$
0%
0&
1)
1*
#19830000
#21480000
X!
0"
X'
0(
#24360000
1%
1&
#27360000
#29010000
0%
0&
#32010000
0!
X"
0'
X(
#33660000
X!
1"
X'
1(
#36540000
1%
1&
#39540000
#41190000
0%
0&
#44190000
#45840000
#48720000
1%
1&
#51720000
0!
X"
0'
X(
#53370000
0#
0$
0%
0&
0)
0*
#56370000
#58020000
X!
1"
X'
1(
